ajson/__init__.py
ajson/ajson.py
ajson/sim/JSON.py
ajson/sim/__init__.py
ajson/sim/compat.py
ajson/sim/decoder.py
ajson/sim/encoder.py
ajson/sim/errors.py
ajson/sim/ordered_dict.py
ajson/sim/raw_json.py
ajson/sim/scanner.py
ajson/sim/tool.py
aestate_json-1.0.3.dist-info/LICENSE
aestate_json-1.0.3.dist-info/METADATA
aestate_json-1.0.3.dist-info/WHEEL
aestate_json-1.0.3.dist-info/top_level.txt
aestate_json-1.0.3.dist-info/RECORD
