Metadata-Version: 2.1
Name: aestate-json
Version: 1.0.3
Summary: Aestate Framework for Python,You can see:https://gitee.com/canotf/aestate
Home-page: https://gitee.com/canotf/aestate-json
Author: CACode
Author-email: cacode@163.com
License: Apache License 2.0
Project-URL: Bug Tracker, https://gitee.com/canotf/aestate-json/issues
Platform: UNKNOWN
Classifier: Programming Language :: Python :: 3
Classifier: License :: OSI Approved :: MIT License
Classifier: Operating System :: OS Independent
Requires-Python: >=3.6
